cmd2/__init__.py
cmd2/argparse_completer.py
cmd2/argparse_custom.py
cmd2/clipboard.py
cmd2/cmd2.py
cmd2/colors.py
cmd2/command_definition.py
cmd2/constants.py
cmd2/decorators.py
cmd2/exceptions.py
cmd2/history.py
cmd2/parsing.py
cmd2/plugin.py
cmd2/py.typed
cmd2/py_bridge.py
cmd2/rich_utils.py
cmd2/rl_utils.py
cmd2/string_utils.py
cmd2/styles.py
cmd2/terminal_utils.py
cmd2/transcript.py
cmd2/utils.py
cmd2-3.0.0.dist-info/licenses/LICENSE
cmd2-3.0.0.dist-info/METADATA
cmd2-3.0.0.dist-info/WHEEL
cmd2-3.0.0.dist-info/top_level.txt
cmd2-3.0.0.dist-info/RECORD
