Metadata-Version: 2.4
Name: cmd2
Version: 3.0.0
Summary: cmd2 - quickly build feature-rich and user-friendly interactive command line applications in Python
Author: cmd2 Contributors
License-Expression: MIT
Keywords: CLI,cmd,command,interactive,prompt,Python
Classifier: Development Status :: 5 - Production/Stable
Classifier: Environment :: Console
Classifier: Operating System :: OS Independent
Classifier: Intended Audience :: Developers
Classifier: Intended Audience :: System Administrators
Classifier: Programming Language :: Python :: 3 :: Only
Classifier: Programming Language :: Python :: 3.10
Classifier: Programming Language :: Python :: 3.11
Classifier: Programming Language :: Python :: 3.12
Classifier: Programming Language :: Python :: 3.13
Classifier: Programming Language :: Python :: 3.14
Classifier: Programming Language :: Python :: 3.15
Classifier: Programming Language :: Python :: Free Threading :: 3 - Stable
Classifier: Topic :: Software Development :: Libraries :: Python Modules
Requires-Python: >=3.10
License-File: LICENSE
Requires-Dist: backports.strenum; python_version == "3.10"
Requires-Dist: gnureadline>=8; platform_system == "Darwin"
Requires-Dist: pyperclip>=1.8.2
Requires-Dist: pyreadline3>=3.4; platform_system == "Windows"
Requires-Dist: rich>=14.1.0
Requires-Dist: rich-argparse>=1.7.1
Dynamic: license-file
